flamedisx/__init__.py
flamedisx/block_source.py
flamedisx/bounds.py
flamedisx/frozen_reservoir.py
flamedisx/inference.py
flamedisx/likelihood.py
flamedisx/lxe_sources.py
flamedisx/mu_estimation.py
flamedisx/non_asymptotic_inference.py
flamedisx/source.py
flamedisx/templates.py
flamedisx/utils.py
flamedisx/configs/__init__.py
flamedisx/configs/example.py
flamedisx/lux/__init__.py
flamedisx/lux/lux.py
flamedisx/lxe_blocks/__init__.py
flamedisx/lxe_blocks/detection.py
flamedisx/lxe_blocks/double_pe.py
flamedisx/lxe_blocks/energy_spectrum.py
flamedisx/lxe_blocks/quanta_generation.py
flamedisx/lxe_blocks/quanta_splitting.py
flamedisx/lxe_blocks/raw_signals.py
flamedisx/lxe_blocks/reconstruct_signals.py
flamedisx/nest/__init__.py
flamedisx/nest/lxe_sources.py
flamedisx/nest/parameter_calc.py
flamedisx/nest/config/default.ini
flamedisx/nest/lxe_blocks/__init__.py
flamedisx/nest/lxe_blocks/detection.py
flamedisx/nest/lxe_blocks/double_pe.py
flamedisx/nest/lxe_blocks/energy_spectrum.py
flamedisx/nest/lxe_blocks/final_signals.py
flamedisx/nest/lxe_blocks/pe_detection.py
flamedisx/nest/lxe_blocks/quanta_splitting.py
flamedisx/nest/lxe_blocks/secondary_quanta_generation.py
flamedisx/tfp_files/__init__.py
flamedisx/tfp_files/skew_gaussian.py
flamedisx/tfp_files/truncated_skew_gaussian_cc.py
flamedisx/xenon/__init__.py
flamedisx/xenon/data.py
flamedisx/xenon/itp_map.py
flamedisx/xenon/resource.py
flamedisx/xenon/x1t_sr0.py
flamedisx/xenon/x1t_sr1.py
tests/__init__.py
tests/test_inference.py
tests/test_likelihood.py
tests/test_mock_inference.py
tests/test_mu.py
tests/test_nest.py
tests/test_source.py
tests/test_template.py
tests/test_utils.py
flamedisx-2.1.0.dist-info/LICENSE
flamedisx-2.1.0.dist-info/METADATA
flamedisx-2.1.0.dist-info/WHEEL
flamedisx-2.1.0.dist-info/top_level.txt
flamedisx-2.1.0.dist-info/RECORD
