Metadata-Version: 2.1
Name: flamedisx
Version: 2.1.0
Summary: Fast likelihood analysis in more dimensions for xenon TPCs
Home-page: https://github.com/FlamTeam/flamedisx
Author: Flamedisx developers
Classifier: Development Status :: 4 - Beta
Classifier: License :: OSI Approved :: BSD License
Classifier: Natural Language :: English
Classifier: Programming Language :: Python :: 3.6
Classifier: Intended Audience :: Science/Research
Classifier: Programming Language :: Python :: Implementation :: CPython
Classifier: Topic :: Scientific/Engineering :: Physics
Requires-Python: >=3.6
License-File: LICENSE
Requires-Dist: numpy
Requires-Dist: scipy
Requires-Dist: pandas
Requires-Dist: multihist
Requires-Dist: wimprates >=0.3.1
Requires-Dist: tqdm
Requires-Dist: tensorflow >=2.2.0
Requires-Dist: tensorflow-probability >=0.8.0
Requires-Dist: iminuit
Provides-Extra: docs
Requires-Dist: sphinx ; extra == 'docs'
Requires-Dist: sphinx-rtd-theme ; extra == 'docs'
Requires-Dist: nbsphinx ; extra == 'docs'
Requires-Dist: recommonmark ; extra == 'docs'
Provides-Extra: strict-deps
Requires-Dist: numpy ==1.26.4 ; extra == 'strict-deps'
Requires-Dist: scipy ==1.12.0 ; extra == 'strict-deps'
Requires-Dist: pandas ==2.2.1 ; extra == 'strict-deps'
Requires-Dist: multihist ==0.6.5 ; extra == 'strict-deps'
Requires-Dist: wimprates ==0.5.0 ; extra == 'strict-deps'
Requires-Dist: tqdm ==4.66.2 ; extra == 'strict-deps'
Requires-Dist: tensorflow ==2.16.1 ; extra == 'strict-deps'
Requires-Dist: tensorflow-probability ==0.24.0 ; extra == 'strict-deps'
Requires-Dist: tf-keras ==2.16.0 ; extra == 'strict-deps'
Requires-Dist: iminuit ==2.25.2 ; extra == 'strict-deps'
